climetlab_weatherbench/__init__.py
climetlab_weatherbench/main.py
climetlab_weatherbench/version
climetlab_weatherbench-0.1.2.dist-info/AUTHORS.rst
climetlab_weatherbench-0.1.2.dist-info/LICENSE
climetlab_weatherbench-0.1.2.dist-info/METADATA
climetlab_weatherbench-0.1.2.dist-info/WHEEL
climetlab_weatherbench-0.1.2.dist-info/entry_points.txt
climetlab_weatherbench-0.1.2.dist-info/top_level.txt
climetlab_weatherbench-0.1.2.dist-info/zip-safe
climetlab_weatherbench-0.1.2.dist-info/RECORD
