Metadata-Version: 2.1
Name: climetlab-weatherbench
Version: 0.1.2
Summary: A dataset plugin for climetlab for the dataset weatherbench
Home-page: http://github.com/mchantry/climetlab-weatherbench
Author: Matthew Chantry
Author-email: matthew.chantry@ecmwf.int
License: Apache License Version 2.0
Keywords: meteorology
Classifier: Development Status :: 3 - Alpha
Classifier: Intended Audience :: Developers
Classifier: License :: OSI Approved :: Apache Software License
Classifier: Programming Language :: Python :: 3
Classifier: Programming Language :: Python :: 3.7
Classifier: Programming Language :: Python :: 3.8
Classifier: Programming Language :: Python :: 3.9
Classifier: Programming Language :: Python :: Implementation :: CPython
Classifier: Programming Language :: Python :: Implementation :: PyPy
Classifier: Operating System :: OS Independent
License-File: LICENSE
License-File: AUTHORS.rst
Requires-Dist: climetlab >=0.10.0
